shis/__init__.py
shis/server.py
shis/utils.py
shis/templates/index.html
shis/templates/static/favicon.ico
shis/templates/static/jquery.min.js
shis/templates/static/lg.woff
shis/templates/static/lightgallery.min.css
shis/templates/static/lightgallery.min.js
shis/templates/static/loading.gif
shis/templates/static/reset.css
shis/templates/static/style.css
shis-0.1.dist-info/LICENSE.md
shis-0.1.dist-info/METADATA
shis-0.1.dist-info/WHEEL
shis-0.1.dist-info/top_level.txt
shis-0.1.dist-info/RECORD
