Metadata-Version: 2.1
Name: shis
Version: 0.1
Summary: Simple HTTP Image Server
Home-page: https://github.com/nikhilweee/shis/
Author: Nikhil Verma
Author-email: nikhilweee@gmail.com
License: MIT
Project-URL: Documentation, https://shis.readthedocs.io/
Project-URL: Source, https://github.com/nikhilweee/shis/
Platform: UNKNOWN
Classifier: Programming Language :: Python :: 3.6
Classifier: Programming Language :: Python :: 3.7
Classifier: Programming Language :: Python :: 3.8
Classifier: Programming Language :: Python :: 3.9
Classifier: License :: OSI Approved :: MIT License
Classifier: Operating System :: POSIX
Classifier: Development Status :: 4 - Beta
Classifier: Intended Audience :: Developers
Classifier: Intended Audience :: Science/Research
Classifier: Topic :: Scientific/Engineering :: Image Processing
Classifier: Environment :: Console
Classifier: Environment :: MacOS X
Classifier: Environment :: Win32 (MS Windows)
Classifier: Framework :: Sphinx
Classifier: Natural Language :: English
Classifier: Typing :: Typed
Requires-Python: >=3.6
Requires-Dist: Pillow (>=7.0.0)
Requires-Dist: Jinja2
Requires-Dist: tqdm
